{"cameraMode":{"drawMode":0,"name":"Shaded","section":"Shading Mode"},"sceneLighting":true,"audioPlay":false,"sceneViewState":{"showFog":true,"showMaterialUpdate":false,"showSkybox":true,"showFlares":true,"showImageEffects":true,"showParticleSystems":true},"in2DMode":false,"pivot":{"x":5.5937089920043949,"y":-0.618804931640625,"z":1.5556640625},"rotation":{"x":0.15431927144527436,"y":0.13000844419002534,"z":-0.020492378622293474,"w":0.9792157411575317},"size":28.020719528198243,"orthographic":false}